grompy/__init__.py
grompy/transpiler.py
grompy/version.txt
grompy-0.0.4.dist-info/METADATA
grompy-0.0.4.dist-info/WHEEL
grompy-0.0.4.dist-info/licenses/LICENSE
grompy-0.0.4.dist-info/RECORD
